nurikit-0.1.0a16.dist-info/RECORD
nurikit-0.1.0a16.dist-info/WHEEL
nurikit-0.1.0a16.dist-info/METADATA
nurikit-0.1.0a16.dist-info/licenses/LICENSE
nurikit-0.1.0a16.dist-info/licenses/NOTICE.md
nuri/desc.cpython-313-darwin.so
nuri/_version.pyi
nuri/__init__.pyi
nuri/_version.py
nuri/_log_interface.cpython-313-darwin.so
nuri/fmt.cpython-313-darwin.so
nuri/desc.pyi
nuri/__init__.py
nuri/algo.cpython-313-darwin.so
nuri/_log_interface.pyi
nuri/py.typed
nuri/_log_adapter.py
nuri/algo.pyi
nuri/_log_adapter.pyi
nuri/tools/galign.pyi
nuri/tools/__init__.pyi
nuri/tools/__init__.py
nuri/tools/tm.pyi
nuri/tools/tm.cpython-313-darwin.so
nuri/tools/galign.cpython-313-darwin.so
nuri/core/_core.cpython-313-darwin.so
nuri/core/__init__.pyi
nuri/core/_core.pyi
nuri/core/__init__.py
nuri/core/geometry.pyi
nuri/core/geometry.cpython-313-darwin.so
nuri/fmt/__init__.pyi
nuri/fmt/pdb.pyi
nuri/.dylibs/libnuri.dylib
