Metadata-Version: 2.1
Name: nurikit
Version: 0.1.0a16
Summary: *The* fundamental software platform for chem- and bio-informatics
Author-Email: Nuri Jung <jnooree@snu.ac.kr>
Maintainer-Email: Nuri Jung <jnooree@snu.ac.kr>
License:                                  Apache License
Classifier: Development Status :: 3 - Alpha
Classifier: Intended Audience :: Science/Research
Classifier: Intended Audience :: Developers
Classifier: License :: OSI Approved :: Apache Software License
Classifier: Programming Language :: C++
Classifier: Programming Language :: Python :: 3 :: Only
Classifier: Programming Language :: Python :: 3.7
Classifier: Programming Language :: Python :: 3.8
Classifier: Programming Language :: Python :: 3.9
Classifier: Programming Language :: Python :: 3.10
Classifier: Programming Language :: Python :: 3.11
Classifier: Programming Language :: Python :: 3.12
Classifier: Programming Language :: Python :: 3.13
Classifier: Topic :: Software Development :: Libraries
Classifier: Topic :: Scientific/Engineering
Classifier: Topic :: Scientific/Engineering :: Bio-Informatics
Classifier: Topic :: Scientific/Engineering :: Chemistry
Classifier: Operating System :: POSIX :: Linux
Classifier: Operating System :: MacOS :: MacOS X
Project-URL: Documentation, https://nurikit.readthedocs.io/
Project-URL: Repository, https://github.com/seoklab/nurikit.git
Requires-Python: >=3.7
Requires-Dist: numpy
Provides-Extra: test
Requires-Dist: pytest; extra == "test"
Requires-Dist: pytest-xdist; extra == "test"
Requires-Dist: scipy; extra == "test"
Provides-Extra: docs
Requires-Dist: sphinx<8.2; extra == "docs"
Requires-Dist: sphinxcontrib-bibtex; extra == "docs"
Requires-Dist: sphinx-rtd-theme; extra == "docs"
Requires-Dist: urllib3<2.0; extra == "docs"
Requires-Dist: setuptools; extra == "docs"
Provides-Extra: coverage
Requires-Dist: gcovr; extra == "coverage"
